gempaterkini/__init__.py
earthquakeBMKG-0.4.dist-info/LICENSE
earthquakeBMKG-0.4.dist-info/METADATA
earthquakeBMKG-0.4.dist-info/WHEEL
earthquakeBMKG-0.4.dist-info/top_level.txt
earthquakeBMKG-0.4.dist-info/RECORD
